okx_quant/__init__.py
okx_quant/account/__init__.py
okx_quant/account/account.py
okx_quant/bots/__init__.py
okx_quant/bots/grid_bots.py
okx_quant/core/__init__.py
okx_quant/core/core.py
okx_quant/data/__init__.py
okx_quant/data/kline.py
okx_quant/financial_product/__init__.py
okx_quant/financial_product/earn.py
okx_quant/future/__init__.py
okx_quant/future/future.py
okx_quant/spot/__init__.py
okx_quant/spot/spot.py
okx_quant/utils/__init__.py
okx_quant/utils/config_utils.py
okx_quant/utils/request_utils.py
okx_quant/utils/time_utils.py
okx_quant-0.0.14.dist-info/METADATA
okx_quant-0.0.14.dist-info/WHEEL
okx_quant-0.0.14.dist-info/top_level.txt
okx_quant-0.0.14.dist-info/RECORD
