Metadata-Version: 2.1
Name: okx_quant
Version: 0.0.14
Summary: okx quant
Home-page: https://github.com/openhe-hub/okx-quant
Author: openhe
Author-email: hezhewen2004@gmail.com
Classifier: Programming Language :: Python :: 3
Classifier: License :: OSI Approved :: MIT License
Classifier: Operating System :: OS Independent
